ibrahim pdf.py
main.py
ibrahimhahaforpypipackage-1.0.dist-info/METADATA
ibrahimhahaforpypipackage-1.0.dist-info/WHEEL
ibrahimhahaforpypipackage-1.0.dist-info/license.txt
ibrahimhahaforpypipackage-1.0.dist-info/top_level.txt
ibrahimhahaforpypipackage-1.0.dist-info/RECORD
