Metadata-Version: 2.1
Name: ibrahimhahaforpypipackage
Version: 1.0
Summary: this is my file
Home-page: UNKNOWN
Author: DELL
Author-email: zaheeribrahim346@gmail.com
License: license.txt
Platform: UNKNOWN
License-File: license.txt
